LICENSE
MANIFEST.in
README.rst
setup.py
redisrwlock/__init__.py
redisrwlock/__main__.py
redisrwlock/redisrwlock.py
redisrwlock.egg-info/PKG-INFO
redisrwlock.egg-info/SOURCES.txt
redisrwlock.egg-info/dependency_links.txt
redisrwlock.egg-info/requires.txt
redisrwlock.egg-info/top_level.txt
test/test_redisrwlock.py
test/test_redisrwlock_cmp_time.py
test/test_redisrwlock_connection.py