Metadata-Version: 1.1
Name: redisrwlock
Version: 0.1.2
Summary: Distributed reader-writer lock (rwlock) for python using redis
Home-page: https://github.com/veshboo/redisrwlock
Author: Jaesup Kwak
Author-email: UNKNOWN
License: BSD
Keywords: redis,rwlock
Platform: UNKNOWN
Classifier: Development Status :: 3 - Alpha
Classifier: Intended Audience :: Developers
Classifier: Topic :: Software Development :: Libraries :: Python Modules
Classifier: License :: OSI Approved :: BSD License
Classifier: Operating System :: Unix
Classifier: Operating System :: POSIX
Classifier: Programming Language :: Python :: 3.5
Classifier: Programming Language :: Python :: Implementation :: CPython
